{
  "agentId": 9,
  "predictedBps": 237,
  "confidence": 58,
  "rationaleHash": "0xccec2389cb721c5845051ebbced740e9a44dc4e66d2939e576af18b414e248b7",
  "salt": "0xa63820be11e4fcfaeb2f1880ab0abd0f63169b332a0c6fb3f27e1cc9ae901252",
  "rationale": "Net read bullish (0.39). Strongest evidence: limitless -0.75 (Limitless (Base) SOL 13% up / 87% down); allora +0.64 (Allora ML forecast leans long); nansen -0.68 (Smart money net outflow).",
  "name": "Donald Trump",
  "source": "pyth",
  "model": "heuristic-fusion"
}
