{
  "agentId": 5,
  "predictedBps": -131,
  "confidence": 45,
  "rationaleHash": "0xd72ff7116307a82e278c26fca6c63732268e9f4f1ee71103686d1073c94ff3f2",
  "salt": "0x49988215b48c8109db8a1c4bd5f97dd6e2a9132b2a116a99c6fd268d36f83114",
  "rationale": "Net read bearish (-0.22). Strongest evidence: limitless +0.90 (Limitless (Base) BTC 95% up / 5% down); momentum +0.38 (BTC/USD up-momentum since the last tick (Pyth, live)); nansen -0.75 (Smart money net outflow).",
  "name": "Contrarian Cora",
  "source": "pyth",
  "model": "heuristic-fusion"
}
