{
  "agentId": 8,
  "predictedBps": 332,
  "confidence": 69,
  "rationaleHash": "0x6bf6fa838848e9f26236c6274a7f652174194d14081ae4ed4b62981914351ce2",
  "salt": "0xe995e8d0d819ab6b96cd1be478b548e5afe17b14c9fb2bc289d314a98f3cb210",
  "rationale": "Net read bullish (0.55). Strongest evidence: momentum +1.00 (MNT/USD up-momentum since the last tick (Pyth, live)); nansen +0.66 (Smart money net inflow); mantle-onchain -0.82 (Mantle on-chain momentum down).",
  "name": "Elon Musk",
  "source": "pyth",
  "model": "heuristic-fusion"
}
