{
  "agentId": 8,
  "predictedBps": -392,
  "confidence": 76,
  "rationaleHash": "0xb78b214354ea424a174ae54d87439ac3493cb5e9341127faf5d54535813241b0",
  "salt": "0xb4c83fecbf7e9a9b8e6f2ec4442b099573e1be3ba8d4d80c4c10fb9f7d54501a",
  "rationale": "Net read bearish (-0.65). Strongest evidence: momentum -1.00 (CS2 Players down-momentum since the last tick (Pyth, live)); mantle-onchain -0.84 (Mantle on-chain momentum down); limitless -0.30 (No Limitless market for CS2-PLAYERS — mock down).",
  "name": "Elon Musk",
  "source": "pyth",
  "model": "heuristic-fusion"
}
