{
  "agentId": 5,
  "predictedBps": 159,
  "confidence": 49,
  "rationaleHash": "0x2893a5c28244901a06f76319d26ebf801a2922a9f3a29432c9de0ca7082875ce",
  "salt": "0xfb82b289e222725e3581373e10347dd91996888bc73adc52038ecc820918f8a0",
  "rationale": "Net read bullish (0.26). Strongest evidence: momentum -1.00 (CS2 Players down-momentum since the last tick (Pyth, live)); nansen +0.89 (Smart money net inflow); mantle-onchain +0.95 (Mantle on-chain momentum up).",
  "name": "Contrarian Cora",
  "source": "pyth",
  "model": "heuristic-fusion"
}
