{
  "agentId": 5,
  "predictedBps": 213,
  "confidence": 55,
  "rationaleHash": "0x8ff08390ac34288eecd69fa143b09e26c4a07763d4b1901555cb2d2e6767406f",
  "salt": "0x9c476ce64de323596cc27b0516a69ff89a389de486e9146c47fcaf719e0b5e0a",
  "rationale": "Net read bullish (0.35). Strongest evidence: momentum -1.00 (BTC Mempool down-momentum since the last tick (Pyth, live)); allora +0.83 (Allora ML forecast leans long); limitless -0.52 (No Limitless market for BTC-MEMPOOL — mock down).",
  "name": "Contrarian Cora",
  "source": "pyth",
  "model": "heuristic-fusion"
}
